{
    "diary_number": "169492013",
    "filed_on": "28-05-2013 01:52 PM",
    "slp_no": "019633 - 019641 / 2013",
    "registered_on": "10-06-2013",
    "verified_on": "",
    "last_listed_on": "16-01-2019",
    "last_hearing_judges": "REGISTRAR (J) - II",
    "status": "Pending - (Motion Hearing   [AFTER NOTICE (FOR ADMISSION) - CIVIL CASES]) List before court/bench-Ord dt:16-01-2019 ",
    "tentative_date": "09-09-2022",
    "category": "0615-Service Matters : Recruitment/Transfer/Compassionate Appointment",
    "act": "",
    "petitioner": [
        "VIDYA K. S/D/W/Thru:- SHIVAKUAMR H.M.",
        "SMT. ASHA G. S/D/W/Thru:- SUHAS Y.S.",
        "SMT. MANJULA KADAPATTI S/D/W/Thru:- LATE SRI GIRIMALLAPPA KADAPATTI",
        "SMT. MANJLA SHESHAGIRI",
        "SMT. NAVANEETHA S/D/W/Thru:- DR. V. CHANDRASEKHAR"
    ],
    "respondents": [
        "THE STATE OF KARNATAKA",
        "THE DIRECTOR OF COLLEGIATE EDUCATION IN KARNATAKA",
        "THE COMMISSIONER, DEPARTMENT OF COLLEGIATE EDUCATION",
        "THE KARNATAKA PUBLIC SERVICE COMMISSION THR. SECRETARY",
        "THE VICE CHANCELLOR BANGALORE UNIVERSITY",
        "THE UNIVERSITY GRANTS COMMISSION (UGC) REP. ITS SECRETARY",
        "SMT. VISHANDEVI HARBHAGAWANDAS DHANOOMAL REP. BY ITS PRINCIPAL",
        "SMT. MALATI MUNIRAJU PAWAD S/D/W/Thru:- SHRI H.S. NATARAJ"
    ],
    "pet_advocate": [
        "KUMAR GARG[P-1]"
    ],
    "resp_advocate": [
        "V. N. RAGHUPATHY[R-1]",
        "BIMLESH KUMAR SINGH[R-1]",
        "DEVASA & CO.[R-1]",
        "ARJUN HARKAULI[R-1]",
        "ANJANA CHANDRASHEKAR[R-1]"
    ],
    "u_section": " "
}