[
    {
        "S.No": "1",
        "Process Id": "80204/2020-08-11",
        "Notice Type": "Dismissal Letter",
        "Name": "DHANANJAY GARG-2300Copy",
        "State / District": "NEW DELHI        /DELHI",
        "Station": "",
        "Issue Date": "11-08-2020",
        "Returnable Date": "30-11--0001",
        "Dispatch Date": "",
        "Serve Date": "",
        "Ack. Date": "",
        "Served/Unserved": ""
    },
    {
        "S.No": "2",
        "Process Id": "80204/2020-08-11",
        "Notice Type": "Dismissal Letter",
        "Name": "Through HIGH COURT OF UTTARAKHAND AT NAINITAL UTTARAKHAND",
        "State / District": "NAINITAL           /UTTARAKHAND",
        "Station": "",
        "Issue Date": "11-08-2020",
        "Returnable Date": "30-11--0001",
        "Dispatch Date": "",
        "Serve Date": "",
        "Ack. Date": "",
        "Served/Unserved": ""
    }
]