{
    "diary_number": "154172020",
    "filed_on": "23-07-2020 12:57 PM",
    "slp_no": "",
    "registered_on": "05-08-2020",
    "verified_on": "07-08-2020",
    "last_listed_on": "28-08-2020",
    "last_hearing_judges": "HON'BLE MR. JUSTICE ASHOK BHUSHAN, HON'BLE MR. JUSTICE R. SUBHASH REDDY and HON'BLE MR. JUSTICE M.R. SHAH",
    "status": "DISPOSED (Motion Hearing   FOR JUDGEMENT) Disposed off-Ord dt:28-08-2020  (Disposal Date: 28-08-2020, Month: 8, Year: 2020)  JUDGES: HON'BLE MR. JUSTICE ASHOK BHUSHAN, HON'BLE MR. JUSTICE R. SUBHASH REDDY, HON'BLE MR. JUSTICE M.R. SHAH <span style=\"color:green;\">Judgement Pronaunced by : HON'BLE MR. JUSTICE ASHOK BHUSHAN of the bench comprising : HON'BLE MR. JUSTICE ASHOK BHUSHAN, HON'BLE MR. JUSTICE R. SUBHASH REDDY, HON'BLE MR. JUSTICE M.R. SHAH</span>",
    "tentative_date": "",
    "category": "0812-Letter Petition & Pil Matters : Others",
    "act": "",
    "petitioner": [
        "SARTHAK MEHTA S/D/W/Thru:- I.N.MEHTA",
        "YASHWANT THORAT S/D/W/Thru:- DHANAJI THORAT",
        "APOORVA MAHESHWARI S/D/W/Thru:- JAWAHAR LAL MAHESHWARI"
    ],
    "respondents": [
        "UNIVERSITY GRANTS COMMISSION, (UGC)",
        "UNION OF INDIA",
        "UNION OF INDIA",
        "UNION OF INDIA"
    ],
    "pet_advocate": [
        ""
    ],
    "resp_advocate": [
        "SACHIN PATIL",
        "APOORV KURUP[R-1]"
    ],
    "u_section": " "
}