{
    "diary_number": "188922017",
    "filed_on": "30-06-2017 12:00 AM",
    "slp_no": "018938 - 018942 / 2017",
    "registered_on": "21-07-2017",
    "verified_on": "",
    "last_listed_on": "17-07-2018",
    "last_hearing_judges": "HON'BLE MR. JUSTICE KURIAN JOSEPH and HON'BLE MR. JUSTICE SANJAY KISHAN KAUL",
    "status": "DISPOSED (Motion Hearing   [AFTER NOTICE (FOR ADMISSION) - CIVIL CASES]) Disposed off-Ord dt:17-07-2018  (Disposal Date: 17-07-2018, Month: 7, Year: 2018)  JUDGES: HON'BLE MR. JUSTICE KURIAN JOSEPH, HON'BLE MR. JUSTICE SANJAY KISHAN KAUL",
    "tentative_date": "",
    "category": "0607-Service Matters : Condition of service",
    "act": "",
    "petitioner": [
        "THE UNIVERSITY OF KERALA REGISTRAR"
    ],
    "respondents": [
        "DR. D. RADHAKRISHNAN PILLAI S/D/W/Thru:- LATE K. DAMODHARAN PILLAI",
        "TRAVANCORE DEVASWOM BOARD SECRETARY",
        "UNIVERSITY GRANTS COMMISSION (UGC) SECRETARY",
        "REGISTRAR MAHATMA GANDHI UNIVERSITY",
        "DR. S. SIVAKUMAR",
        "K.P. BALACHANDRAN",
        "DR. C. BHUVANENDRAN",
        "R. JAYACHANDRAN",
        "DR. VIJAYALEKSHMI S/D/W/Thru:- DR. BALACHANDRAN",
        "UNIVERSITY GRANTS COMMISSION SECRETARY",
        "TRAVANCORE DEVASWOM BOARD SECRETARY",
        "MAHATMA GANDHI UNIVERSITY REGISTRAR",
        "DR. S. SIVA KUMAR",
        "DR. K. BALACHANDRAN",
        "DR. C. BHUVANACHANDRAN",
        "JAYACHANDRAN",
        "DR. K. MOHANAKUMAR",
        "THE STATE OF KERALA     SECRETARY TO GOVERNMENT OF KERALA, HIGHER EDUCATION DEPARTMENT",
        "UNIVERSITY GRANTS COMMISSION (UGC) SECRETARY",
        "REGISTRAR MAHATMA GANDHI UNIVERSITY THE STATE OF KERALA",
        "THE STATE OF KERALA TRAVANCORE DEVASWOM BOARD SECRETARY",
        "DR. C. BHUVANACHANDRAN",
        "R. JAYACHANDRAN",
        "DR. S. SIVAKUMAR",
        "K.P. BALACHANDRAN",
        "DR. K. MOHANA KUMAR",
        "THE STATE OF KERALA     SECRETARY TO GOVERNMENT OF KERALA, HIGHER EDUCATION DEPARTMENT",
        "UNIVERSITY GRANTS COMMISSION (UGC) SECRETARY",
        "REGISTRAR MAHATMA GANDHI UNIVERSITY",
        "TRAVANCORE DEVASWOM BOARD SECRETARY",
        "DR. M.N. RADHAKRISHNAN NAIR",
        "DR. P.P. CHANDRASEKHARAN PILLAI",
        "PROF. S. LEKHA",
        "PROF. K. SOMAN PILLAI",
        "DR. D. RADHKRISHNA PILLAI S/D/W/Thru:- LATE K. DAMODHARAN PILLAI",
        "THE STATE OF KERALA     SECRETARY, HIGHER EDUCATION DEPARTMENT",
        "TRAVANCORE DEVASWOM BOARD SECRETARY",
        "UNIVERSITY GRANTS COMMISSION (UGC) SECRETARY",
        "REGISTRAR MAHATMA GANDHI UNIVERSITY THE STATE OF KERALA",
        "DR. M.N. RADHAKRISHNAN",
        "DR. P.P. CHANDRASEKHARAN PILLAI",
        "PROF. K. SOMAN PILLAI",
        "PROF. S. LEKHA"
    ],
    "pet_advocate": [
        "V. DINESH"
    ],
    "resp_advocate": [
        "HIMINDER LAL[caveat]",
        "HIMINDER LAL[R-17]",
        "RESHMI REA SINHA[R-1]",
        "G. PRAKASH[R-36]",
        "BALAJI SRINIVASAN[R-28]",
        "G. PRAKASH[R-12]"
    ],
    "u_section": " "
}