[
    {
        "CL Date": "17-07-2018",
        "Misc./Regular": "Misc.",
        "Stage": "[AFTER NOTICE (FOR ADMISSION) - CIVIL CASES]",
        "Purpose": "Fixed Date by Court",
        "Proposed/ List in": "Judge",
        "Judges": "HON'BLE MR. JUSTICE KURIAN JOSEPH and HON'BLE MR. JUSTICE SANJAY KISHAN KAUL",
        "IA": "5/2017, 9/2017, ",
        "Remarks": "Disposed off",
        "Listed": "LISTED"
    },
    {
        "CL Date": "08-05-2018",
        "Misc./Regular": "Misc.",
        "Stage": "[AFTER NOTICE (FOR ADMISSION) - CIVIL CASES]",
        "Purpose": "Fixed Date by Court",
        "Proposed/ List in": "Judge",
        "Judges": "HON'BLE MR. JUSTICE KURIAN JOSEPH and HON'BLE MR. JUSTICE MOHAN M. SHANTANAGOUDAR",
        "IA": "5/2017, 9/2017, ",
        "Remarks": "List On (Date) [17-07-2018]",
        "Listed": "LISTED"
    },
    {
        "CL Date": "19-04-2018",
        "Misc./Regular": "Misc.",
        "Stage": "[AFTER NOTICE (FOR ADMISSION) - CIVIL CASES]",
        "Purpose": "Fixed Date by Court",
        "Proposed/ List in": "Judge",
        "Judges": "HON'BLE MR. JUSTICE KURIAN JOSEPH, HON'BLE MR. JUSTICE MOHAN M. SHANTANAGOUDAR and HON'BLE MR. JUSTICE NAVIN SINHA",
        "IA": "",
        "Remarks": "List On (Date) [08-05-2018]",
        "Listed": "LISTED"
    },
    {
        "CL Date": "18-04-2018",
        "Misc./Regular": "Misc.",
        "Stage": "[AFTER NOTICE (FOR ADMISSION) - CIVIL CASES]",
        "Purpose": "Fixed Date by Court",
        "Proposed/ List in": "Judge",
        "Judges": "HON'BLE MR. JUSTICE KURIAN JOSEPH, HON'BLE MR. JUSTICE MOHAN M. SHANTANAGOUDAR and HON'BLE MR. JUSTICE NAVIN SINHA",
        "IA": "5/2017, 9/2017, ",
        "Remarks": "List On (Date) [19-04-2018]",
        "Listed": "LISTED"
    },
    {
        "CL Date": "10-04-2018",
        "Misc./Regular": "Misc.",
        "Stage": "[AFTER NOTICE (FOR ADMISSION) - CIVIL CASES]",
        "Purpose": "Fixed Date by Court",
        "Proposed/ List in": "Judge",
        "Judges": "HON'BLE MR. JUSTICE KURIAN JOSEPH, HON'BLE MR. JUSTICE MOHAN M. SHANTANAGOUDAR and HON'BLE MR. JUSTICE NAVIN SINHA",
        "IA": "5/2017, 9/2017, ",
        "Remarks": "List On (Date) [18-04-2018]",
        "Listed": "LISTED"
    },
    {
        "CL Date": "16-01-2018",
        "Misc./Regular": "Misc.",
        "Stage": "[DEFAULT / OTHER MATTERS]",
        "Purpose": "IA",
        "Proposed/ List in": "Chamber",
        "Judges": "HON'BLE MR. JUSTICE L. NAGESWARA RAO",
        "IA": "",
        "Remarks": "",
        "Listed": "LISTED"
    },
    {
        "CL Date": "16-01-2018",
        "Misc./Regular": "Misc.",
        "Stage": "[DEFAULT / OTHER MATTERS]",
        "Purpose": "IA",
        "Proposed/ List in": "Chamber",
        "Judges": "HON'BLE MR. JUSTICE L. NAGESWARA RAO",
        "IA": "5/2017, 9/2017, ",
        "Remarks": "",
        "Listed": "LISTED"
    },
    {
        "CL Date": "23-11-2017",
        "Misc./Regular": "Misc.",
        "Stage": "[ORDERS (INCOMPLETE MATTERS / IAs / CRLMPs)]",
        "Purpose": "Ordinary",
        "Proposed/ List in": "Registrar",
        "Judges": "REGISTRAR (J) - II",
        "IA": "5/2017, 9/2017, ",
        "Remarks": "",
        "Listed": "LISTED"
    }
]