[
    {
        "CL Date": "30-07-2019",
        "Misc./Regular": "Misc.",
        "Stage": "[AFTER NOTICE (FOR ADMISSION) - CIVIL CASES]",
        "Purpose": "Fixed Date by Court",
        "Proposed/ List in": "Judge",
        "Judges": "HON'BLE MR. JUSTICE ASHOK BHUSHAN and HON'BLE MR. JUSTICE NAVIN SINHA",
        "IA": "71722/2019,",
        "Remarks": "Dismissed",
        "Listed": "LISTED"
    },
    {
        "CL Date": "02-07-2019",
        "Misc./Regular": "Misc.",
        "Stage": "[AFTER NOTICE (FOR ADMISSION) - CIVIL CASES]",
        "Purpose": "Fixed Date by Court",
        "Proposed/ List in": "Judge",
        "Judges": "HON'BLE MR. JUSTICE ASHOK BHUSHAN and HON'BLE MR. JUSTICE NAVIN SINHA",
        "IA": "71722/2019,",
        "Remarks": "List On (Date) [30-07-2019]",
        "Listed": "LISTED"
    },
    {
        "CL Date": "01-05-2019",
        "Misc./Regular": "Misc.",
        "Stage": "[AFTER NOTICE (FOR ADMISSION) - CIVIL CASES]",
        "Purpose": "Fixed Date by Court",
        "Proposed/ List in": "Judge",
        "Judges": "HON'BLE MR. JUSTICE ASHOK BHUSHAN and HON'BLE MR. JUSTICE K.M. JOSEPH",
        "IA": "",
        "Remarks": "List On (Date) [02-07-2019]",
        "Listed": "LISTED"
    },
    {
        "CL Date": "05-04-2019",
        "Misc./Regular": "Misc.",
        "Stage": "[AFTER NOTICE (FOR ADMISSION) - CIVIL CASES]",
        "Purpose": "Next Week / Week Commencing / C.O.Week",
        "Proposed/ List in": "Judge",
        "Judges": "HON'BLE MR. JUSTICE ASHOK BHUSHAN and HON'BLE MR. JUSTICE K.M. JOSEPH",
        "IA": "",
        "Remarks": "List On (Date) [01-05-2019]",
        "Listed": "LISTED"
    },
    {
        "CL Date": "27-08-2018",
        "Misc./Regular": "Misc.",
        "Stage": "[FRESH (FOR ADMISSION) - CIVIL CASES]",
        "Purpose": "FRESH",
        "Proposed/ List in": "Judge",
        "Judges": "HON'BLE MR. JUSTICE A.K. SIKRI and HON'BLE MR. JUSTICE ASHOK BHUSHAN",
        "IA": "",
        "Remarks": "Notice Returnable [D:0,W:6,M:0]",
        "Listed": "LISTED"
    }
]