{
    "diary_number": "222782017",
    "filed_on": "26-07-2017 12:09 PM",
    "slp_no": "020713 - / 2017",
    "registered_on": "14-08-2017",
    "verified_on": "18-08-2017",
    "last_listed_on": "25-08-2017",
    "last_hearing_judges": "HON'BLE THE CHIEF JUSTICE RANJAN GOGOI and HON'BLE MR. JUSTICE NAVIN SINHA",
    "status": "DISPOSED (Motion Hearing   [FRESH (FOR ADMISSION) - CIVIL CASES]) Dismissed-Ord dt:25-08-2017  (Disposal Date: 25-08-2017, Month: 8, Year: 2017)  JUDGES: HON'BLE THE CHIEF JUSTICE RANJAN GOGOI, HON'BLE MR. JUSTICE NAVIN SINHA",
    "tentative_date": "",
    "category": "0613-Service Matters : Others",
    "act": "",
    "petitioner": [
        "RENU BALA S/D/W/Thru:- NARENDER"
    ],
    "respondents": [
        "THE STATE OF HARYANA HIGHER EDUCATION DEPARTMENT PRINCIPAL SECRETARY",
        "DIRECTOR GENERAL, HIGH EDUCATION",
        "UNIVERSITY GRANTS COMMISSION, THROUGH ITS SECRETARY",
        "PRINCIPAL, GOERNMENT P.G. COLLEGE",
        "HEAD OF THE DEPARTMENT, GEOGRAPHY GOVERNMENT PG COLLEGE"
    ],
    "pet_advocate": [
        "KISHOR SINGH"
    ],
    "resp_advocate": [],
    "u_section": " "
}