{
    "diary_number": "108772016",
    "filed_on": "28-03-2016 05:54 PM",
    "slp_no": "010881 / 2016",
    "registered_on": "19-04-2016",
    "verified_on": "",
    "last_listed_on": "28-04-2022",
    "last_hearing_judges": "HON'BLE MR. JUSTICE S. ABDUL NAZEER and HON'BLE MR. JUSTICE VIKRAM NATH",
    "status": "Pending - (Final Hearing) List After (Weeks) (8)-Ord dt:28-04-2022 ",
    "tentative_date": "",
    "category": "0613-Service Matters : Others",
    "act": "",
    "petitioner": [
        "PROF. AMBHORE ASHOK GANGARAM . S/D/W/Thru:- ASHOK GANGARAM",
        "PROF. BHALERAO GOVIND PADMAKARRAO S/D/W/Thru:- GOVIND PADMAKARRAO",
        "PROF. GHAN PRAMOD KISHANRAO S/D/W/Thru:- PRABHAKAR BALABHAU",
        "PROF. DESAI PRABHAKAR BALABHAU S/D/W/Thru:- PRABHAKAR BALABHAU",
        "PROF. DHARWADKAR DEEPAK SUDHAKAR S/D/W/Thru:- DEEPAK SUDHAKAR",
        "PROF. SHINDE HEMANT TRIMBAKRAO S/D/W/Thru:- HEMANT TRIMBAKRAO",
        "PROF. GAIKWAD BALASAHEB JANARDHAN S/D/W/Thru:- BALASAHEB JANARDHAN",
        "PROF. NAVGANKAR RAJABHAU VENKATESHRAO S/D/W/Thru:- RAJABHAU VENKATESHRAO",
        "PROF. MUKTE ZODABARAO S/D/W/Thru:- RAMDAS ZODABARAO",
        "PROF. DEVKATE PARAJI S/D/W/Thru:- SAHEBRAO PARAJI"
    ],
    "respondents": [
        "UNIVERSITY GRANTS COMMISSION THROUGH ITS CHAIRMAN",
        "THE STATE OF MAHARASHTRA SECRETARY, HIGHER AND TECHNICAL EDUCATION DEPARTMENT ..",
        "DIRECTOR OF HIGHER EDUCATION ..",
        "JOINT DIRECTOR OF HIGHER EDUCATION ..",
        "SHREE RAMANAND TEERTH MARATHWADA UNIVERSITY THROUGH ITS REGISTRAR",
        "TOSHINWAL ARTS AND COMMERCE COLLEGE THROUGH ITS PRINCIPAL",
        "SHREE SHIVAJI SHIKSHAN PRASARAK MANDAL THROUGH ITS PRINCIPAL",
        "NAGNATH ARTS AND SCIENCE COLLEGE THROUGH ITS PRINCIPAL"
    ],
    "pet_advocate": [
        "BHAT"
    ],
    "resp_advocate": [
        "AMOL B. KARANDE"
    ],
    "u_section": " "
}