{
    "diary_number": "389742019",
    "filed_on": "25-10-2019 03:05 PM",
    "slp_no": "026909 - / 2019",
    "registered_on": "14-11-2019",
    "verified_on": "18-11-2019",
    "last_listed_on": "22-11-2019",
    "last_hearing_judges": "HON'BLE MR. JUSTICE NAVIN SINHA and HON'BLE MR. JUSTICE KRISHNA MURARI",
    "status": "DISPOSED (Motion Hearing   [FRESH (FOR ADMISSION) - CIVIL CASES]) Dismissed-Ord dt:22-11-2019  (Disposal Date: 22-11-2019, Month: 11, Year: 2019)  JUDGES: HON'BLE MR. JUSTICE NAVIN SINHA, HON'BLE MR. JUSTICE KRISHNA MURARI",
    "tentative_date": "",
    "category": "4003-Admission/Transfer To Engineering And Medical Colleges : Others",
    "act": "",
    "petitioner": [
        "HIMANSHU S/D/W/Thru:- JAGDISH PRASAD",
        "RONAK SHARMA S/D/W/Thru:- SALEK CHAND SHARMA",
        "SHUBHAM SHISODIA S/D/W/Thru:- C.K. SHISODIA"
    ],
    "respondents": [
        "UNION OF INDIA",
        "STATE OF UTTAR PRADESH",
        "THE DIRECTOR GENERAL",
        "THE OVERSIGHT COMMITTEE",
        "THE SECRETARY",
        "THE PRINCIPAL SECRETARY",
        "THE ADG (ME)",
        "VENKATESHWARA INSTITUTE OF MEDICAL SCIENCES",
        "UNIVERSITY GRANTS COMMISSION",
        "SUPERINTENDENT OF POLICE",
        "GLORY SAJI S/D/W/Thru:- SAJI SAMUEL",
        "ARJAW OJHA S/D/W/Thru:- RAMENDRA PRASAD",
        "MANTO KONYAK S/D/W/Thru:- NOKHO NONYAK"
    ],
    "pet_advocate": [
        "AMBWANI"
    ],
    "resp_advocate": [],
    "u_section": " "
}