{
    "INTERLOCUTARY APPLICATION(s)": {
        "0": {
            "Reg. No./I.A. No.": "101126/2017",
            "Particular": "PERMISSION TO FILE PETITION (SLP/TP/WP/..)",
            "Remark": "",
            "Filed By": "ANUPAM LAL DAS",
            "Filing Date": "05-10-2017",
            "Sr. No.": "1",
            "Status.": "D",
            "Entered On": "05-10-2017 16:38:18"
        },
        "1": {
            "Reg. No./I.A. No.": "101127/2017",
            "Particular": "CONDONATION OF DELAY IN FILING",
            "Remark": "",
            "Filed By": "ANUPAM LAL DAS",
            "Filing Date": "05-10-2017",
            "Sr. No.": "2",
            "Status.": "D",
            "Entered On": "05-10-2017 16:38:51"
        },
        "2": {
            "Reg. No./I.A. No.": "101129/2017",
            "Particular": "EXEMPTION FROM FILING C/C OF THE IMPUGNED JUDGMENT",
            "Remark": "",
            "Filed By": "ANUPAM LAL DAS",
            "Filing Date": "05-10-2017",
            "Sr. No.": "3",
            "Status.": "P",
            "Entered On": "05-10-2017 16:39:06"
        },
        "3": {
            "Reg. No./I.A. No.": "101135/2017",
            "Particular": "PERMISSION TO FILE ADDITIONAL DOCUMENTS/FACTS/ANNEXURES",
            "Remark": "",
            "Filed By": "ANUPAM LAL DAS",
            "Filing Date": "05-10-2017",
            "Sr. No.": "4",
            "Status.": "P",
            "Entered On": "05-10-2017 16:40:40"
        },
        "4": {
            "Reg. No./I.A. No.": "102057/2017",
            "Particular": "PERMISSION TO FILE ADDITIONAL DOCUMENTS/FACTS/ANNEXURES",
            "Remark": "",
            "Filed By": "ANUPAM LAL DAS",
            "Filing Date": "07-10-2017",
            "Sr. No.": "5",
            "Status.": "P",
            "Entered On": "07-10-2017 11:08:57"
        },
        "5": {
            "Reg. No./I.A. No.": "427/2018",
            "Particular": "MODIFICATION",
            "Remark": "I A FOR MODIFICATION",
            "Filed By": "GAGAN GUPTA",
            "Filing Date": "04-01-2018",
            "Sr. No.": "6",
            "Status.": "P",
            "Entered On": "04-01-2018 14:20:20"
        }
    },
    "OTHER DOCUMENT(s)": {
        "0": {
            "Doc. No.": "111075/2017",
            "Document Type": "PROCESS FEE",
            "Filed By": "ANUPAM LAL DAS",
            "Filing Date": "30-10-2017 11:39 AM",
            "Enter By": "DINESH KUMAR SHARMA I30-10-2017 11:39 AM"
        },
        "1": {
            "Doc. No.": "127470/2017",
            "Document Type": "VAKALATNAMA AND MEMO OF APPEARANCE",
            "Filed By": "APOORV KURUP",
            "Filing Date": "27-11-2017 11:29 AM",
            "Enter By": "TARUN27-11-2017 11:29 AM"
        },
        "2": {
            "Doc. No.": "131371/2017",
            "Document Type": "VAKALATNAMA AND MEMO OF APPEARANCE",
            "Filed By": "SANTOSH KUMAR - I",
            "Filing Date": "04-12-2017 12:13 PM",
            "Enter By": "RAVINA04-12-2017 12:13 PM"
        },
        "3": {
            "Doc. No.": "417/2018",
            "Document Type": "VAKALATNAMA AND MEMO OF APPEARANCE",
            "Filed By": "GAGAN GUPTA",
            "Filing Date": "04-01-2018 02:16 PM",
            "Enter By": "DINESH KUMAR SHARMA I04-01-2018 02:16 PM"
        },
        "4": {
            "Doc. No.": "419/2018",
            "Document Type": "COUNTER AFFIDAVIT",
            "Filed By": "GAGAN GUPTA",
            "Filing Date": "04-01-2018 02:17 PM",
            "Enter By": "DINESH KUMAR SHARMA I04-01-2018 02:17 PM"
        },
        "5": {
            "Doc. No.": "81292/2019",
            "Document Type": "VAKALATNAMA AND MEMO OF APPEARANCE",
            "Filed By": "DIKSHA RAI",
            "Filing Date": "14-05-2019 12:57 PM",
            "Enter By": "LAXMAN14-05-2019 12:57 PM"
        },
        "6": {
            "Doc. No.": "143184/2019",
            "Document Type": "VAKALATNAMA AND MEMO OF APPEARANCE",
            "Filed By": "DIKSHA RAI",
            "Filing Date": "17-09-2019 12:48 PM",
            "Enter By": "AMRIT BHOLA17-09-2019 12:48 PM"
        }
    }
}