[
    {
        "S.No": "1",
        "Process Id": "117686/2021-10-08",
        "Notice Type": "due course notice",
        "Name": "ZOHEB HOSSAIN-2389Copy",
        "State / District": "NEW DELHI        /DELHI",
        "Station": "",
        "Issue Date": "08-10-2021",
        "Returnable Date": "15-11-2021",
        "Dispatch Date": "",
        "Serve Date": "",
        "Ack. Date": "",
        "Served/Unserved": ""
    },
    {
        "S.No": "2",
        "Process Id": "117686/2021-10-08",
        "Notice Type": "due course notice",
        "Name": "THE UNIVERSITY GRANTS COMMISSION OF INDIA,ZOHEB HOSSAIN-2389",
        "State / District": "DELHI         /NEW DELHI",
        "Station": "",
        "Issue Date": "08-10-2021",
        "Returnable Date": "15-11-2021",
        "Dispatch Date": "",
        "Serve Date": "",
        "Ack. Date": "",
        "Served/Unserved": ""
    },
    {
        "S.No": "3",
        "Process Id": "117685/2021-10-08",
        "Notice Type": "due course notice",
        "Name": "THE UNIVERSITY OF ALLAHABAD,ZOHEB HOSSAIN-2389",
        "State / District": "UTTAR PRADESH        /",
        "Station": "",
        "Issue Date": "08-10-2021",
        "Returnable Date": "15-11-2021",
        "Dispatch Date": "",
        "Serve Date": "",
        "Ack. Date": "",
        "Served/Unserved": ""
    },
    {
        "S.No": "4",
        "Process Id": "117684/2021-10-08",
        "Notice Type": "due course notice",
        "Name": "UNION OF INDIAZOHEB HOSSAIN-2389",
        "State / District": "DELHI         /NEW DELHI",
        "Station": "",
        "Issue Date": "08-10-2021",
        "Returnable Date": "15-11-2021",
        "Dispatch Date": "",
        "Serve Date": "",
        "Ack. Date": "",
        "Served/Unserved": ""
    }
]