[
    {
        "S.No.": "1",
        "Court": "High Court",
        "Agency State": "MADHYA PRADESH",
        "Agency Code": "HIGH COURT OF M.P PRINCIPAL SEAT AT JABALPUR",
        "Case No.": "WP-8644-2017",
        "Order Date": "08-03-2018",
        "CNR No. /                    Designation": "111",
        "Judge1/ Judge2/ Judge3": "VIJAY KUMAR SHUKLA",
        "Police Station": "",
        "Crime No./ Year": "/ 0",
        "Authority / Organisation / Impugned Order No.": "-//",
        "Judgment Challenged": "Yes",
        "Judgment Type": "Final",
        "Judgment Covered in": "",
        "Vehicle Number": "",
        "Reference court / State / District / No.": "- / - / - / --",
        "Relied Upon court / State / District / No.": "- / - / - / --",
        "Transfer To State / District / No.": "- / - / --",
        "Government Notification State / No. / Date": "- / -- / 01-01-1970"
    },
    {
        "S.No.": "2",
        "Court": "High Court",
        "Agency State": "MADHYA PRADESH",
        "Agency Code": "HIGH COURT OF M.P PRINCIPAL SEAT AT JABALPUR",
        "Case No.": "WP-1665-2017",
        "Order Date": "08-03-2018",
        "CNR No. /                    Designation": "111",
        "Judge1/ Judge2/ Judge3": "VIJAY KUMAR SHUKLA",
        "Police Station": "",
        "Crime No./ Year": "/ 0",
        "Authority / Organisation / Impugned Order No.": "-//",
        "Judgment Challenged": "No",
        "Judgment Type": "-",
        "Judgment Covered in": "",
        "Vehicle Number": "",
        "Reference court / State / District / No.": "- / - / - / --",
        "Relied Upon court / State / District / No.": "- / - / - / --",
        "Transfer To State / District / No.": "- / - / --",
        "Government Notification State / No. / Date": "- / -- / -"
    },
    {
        "S.No.": "3",
        "Court": "High Court",
        "Agency State": "MADHYA PRADESH",
        "Agency Code": "HIGH COURT OF M.P PRINCIPAL SEAT AT JABALPUR",
        "Case No.": "WP-1683-2017",
        "Order Date": "08-03-2018",
        "CNR No. /                    Designation": "111",
        "Judge1/ Judge2/ Judge3": "VIJAY KUMAR SHUKLA",
        "Police Station": "",
        "Crime No./ Year": "/ 0",
        "Authority / Organisation / Impugned Order No.": "-//",
        "Judgment Challenged": "No",
        "Judgment Type": "-",
        "Judgment Covered in": "",
        "Vehicle Number": "",
        "Reference court / State / District / No.": "- / - / - / --",
        "Relied Upon court / State / District / No.": "- / - / - / --",
        "Transfer To State / District / No.": "- / - / --",
        "Government Notification State / No. / Date": "- / -- / -"
    },
    {
        "S.No.": "4",
        "Court": "High Court",
        "Agency State": "MADHYA PRADESH",
        "Agency Code": "HIGH COURT OF M.P PRINCIPAL SEAT AT JABALPUR",
        "Case No.": "WP-2359-2017",
        "Order Date": "08-03-2018",
        "CNR No. /                    Designation": "111",
        "Judge1/ Judge2/ Judge3": "VIJAY KUMAR SHUKLA",
        "Police Station": "",
        "Crime No./ Year": "/ 0",
        "Authority / Organisation / Impugned Order No.": "-//",
        "Judgment Challenged": "No",
        "Judgment Type": "-",
        "Judgment Covered in": "",
        "Vehicle Number": "",
        "Reference court / State / District / No.": "- / - / - / --",
        "Relied Upon court / State / District / No.": "- / - / - / --",
        "Transfer To State / District / No.": "- / - / --",
        "Government Notification State / No. / Date": "- / -- / -"
    },
    {
        "S.No.": "5",
        "Court": "High Court",
        "Agency State": "MADHYA PRADESH",
        "Agency Code": "HIGH COURT OF M.P PRINCIPAL SEAT AT JABALPUR",
        "Case No.": "WP-2423-2017",
        "Order Date": "08-03-2018",
        "CNR No. /                    Designation": "111",
        "Judge1/ Judge2/ Judge3": "VIJAY KUMAR SHUKLA",
        "Police Station": "",
        "Crime No./ Year": "/ 0",
        "Authority / Organisation / Impugned Order No.": "-//",
        "Judgment Challenged": "No",
        "Judgment Type": "-",
        "Judgment Covered in": "",
        "Vehicle Number": "",
        "Reference court / State / District / No.": "- / - / - / --",
        "Relied Upon court / State / District / No.": "- / - / - / --",
        "Transfer To State / District / No.": "- / - / --",
        "Government Notification State / No. / Date": "- / -- / -"
    },
    {
        "S.No.": "6",
        "Court": "High Court",
        "Agency State": "MADHYA PRADESH",
        "Agency Code": "HIGH COURT OF M.P PRINCIPAL SEAT AT JABALPUR",
        "Case No.": "WP-2434-2017",
        "Order Date": "08-03-2018",
        "CNR No. /                    Designation": "111",
        "Judge1/ Judge2/ Judge3": "VIJAY KUMAR SHUKLA",
        "Police Station": "",
        "Crime No./ Year": "/ 0",
        "Authority / Organisation / Impugned Order No.": "-//",
        "Judgment Challenged": "No",
        "Judgment Type": "-",
        "Judgment Covered in": "",
        "Vehicle Number": "",
        "Reference court / State / District / No.": "- / - / - / --",
        "Relied Upon court / State / District / No.": "- / - / - / --",
        "Transfer To State / District / No.": "- / - / --",
        "Government Notification State / No. / Date": "- / -- / -"
    },
    {
        "S.No.": "7",
        "Court": "High Court",
        "Agency State": "MADHYA PRADESH",
        "Agency Code": "HIGH COURT OF M.P PRINCIPAL SEAT AT JABALPUR",
        "Case No.": "WP-2497-2017",
        "Order Date": "08-03-2018",
        "CNR No. /                    Designation": "111",
        "Judge1/ Judge2/ Judge3": "VIJAY KUMAR SHUKLA",
        "Police Station": "",
        "Crime No./ Year": "/ 0",
        "Authority / Organisation / Impugned Order No.": "-//",
        "Judgment Challenged": "No",
        "Judgment Type": "-",
        "Judgment Covered in": "",
        "Vehicle Number": "",
        "Reference court / State / District / No.": "- / - / - / --",
        "Relied Upon court / State / District / No.": "- / - / - / --",
        "Transfer To State / District / No.": "- / - / --",
        "Government Notification State / No. / Date": "- / -- / -"
    },
    {
        "S.No.": "8",
        "Court": "High Court",
        "Agency State": "MADHYA PRADESH",
        "Agency Code": "HIGH COURT OF M.P PRINCIPAL SEAT AT JABALPUR",
        "Case No.": "WP-2589-2017",
        "Order Date": "08-03-2018",
        "CNR No. /                    Designation": "111",
        "Judge1/ Judge2/ Judge3": "VIJAY KUMAR SHUKLA",
        "Police Station": "",
        "Crime No./ Year": "/ 0",
        "Authority / Organisation / Impugned Order No.": "-//",
        "Judgment Challenged": "No",
        "Judgment Type": "-",
        "Judgment Covered in": "",
        "Vehicle Number": "",
        "Reference court / State / District / No.": "- / - / - / --",
        "Relied Upon court / State / District / No.": "- / - / - / --",
        "Transfer To State / District / No.": "- / - / --",
        "Government Notification State / No. / Date": "- / -- / -"
    },
    {
        "S.No.": "9",
        "Court": "High Court",
        "Agency State": "MADHYA PRADESH",
        "Agency Code": "HIGH COURT OF M.P PRINCIPAL SEAT AT JABALPUR",
        "Case No.": "WP-3376-2017",
        "Order Date": "08-03-2018",
        "CNR No. /                    Designation": "111",
        "Judge1/ Judge2/ Judge3": "VIJAY KUMAR SHUKLA",
        "Police Station": "",
        "Crime No./ Year": "/ 0",
        "Authority / Organisation / Impugned Order No.": "-//",
        "Judgment Challenged": "No",
        "Judgment Type": "-",
        "Judgment Covered in": "",
        "Vehicle Number": "",
        "Reference court / State / District / No.": "- / - / - / --",
        "Relied Upon court / State / District / No.": "- / - / - / --",
        "Transfer To State / District / No.": "- / - / --",
        "Government Notification State / No. / Date": "- / -- / -"
    },
    {
        "S.No.": "10",
        "Court": "High Court",
        "Agency State": "MADHYA PRADESH",
        "Agency Code": "HIGH COURT OF M.P PRINCIPAL SEAT AT JABALPUR",
        "Case No.": "WP-4293-2017",
        "Order Date": "08-03-2018",
        "CNR No. /                    Designation": "111",
        "Judge1/ Judge2/ Judge3": "VIJAY KUMAR SHUKLA",
        "Police Station": "",
        "Crime No./ Year": "/ 0",
        "Authority / Organisation / Impugned Order No.": "-//",
        "Judgment Challenged": "No",
        "Judgment Type": "-",
        "Judgment Covered in": "",
        "Vehicle Number": "",
        "Reference court / State / District / No.": "- / - / - / --",
        "Relied Upon court / State / District / No.": "- / - / - / --",
        "Transfer To State / District / No.": "- / - / --",
        "Government Notification State / No. / Date": "- / -- / -"
    },
    {
        "S.No.": "11",
        "Court": "High Court",
        "Agency State": "MADHYA PRADESH",
        "Agency Code": "HIGH COURT OF M.P PRINCIPAL SEAT AT JABALPUR",
        "Case No.": "WP-4942-2017",
        "Order Date": "08-03-2018",
        "CNR No. /                    Designation": "111",
        "Judge1/ Judge2/ Judge3": "VIJAY KUMAR SHUKLA",
        "Police Station": "",
        "Crime No./ Year": "/ 0",
        "Authority / Organisation / Impugned Order No.": "-//",
        "Judgment Challenged": "No",
        "Judgment Type": "-",
        "Judgment Covered in": "",
        "Vehicle Number": "",
        "Reference court / State / District / No.": "- / - / - / --",
        "Relied Upon court / State / District / No.": "- / - / - / --",
        "Transfer To State / District / No.": "- / - / --",
        "Government Notification State / No. / Date": "- / -- / -"
    },
    {
        "S.No.": "12",
        "Court": "High Court",
        "Agency State": "MADHYA PRADESH",
        "Agency Code": "HIGH COURT OF M.P PRINCIPAL SEAT AT JABALPUR",
        "Case No.": "WP-4948-2017",
        "Order Date": "08-03-2018",
        "CNR No. /                    Designation": "111",
        "Judge1/ Judge2/ Judge3": "VIJAY KUMAR SHUKLA",
        "Police Station": "",
        "Crime No./ Year": "/ 0",
        "Authority / Organisation / Impugned Order No.": "-//",
        "Judgment Challenged": "No",
        "Judgment Type": "-",
        "Judgment Covered in": "",
        "Vehicle Number": "",
        "Reference court / State / District / No.": "- / - / - / --",
        "Relied Upon court / State / District / No.": "- / - / - / --",
        "Transfer To State / District / No.": "- / - / --",
        "Government Notification State / No. / Date": "- / -- / -"
    },
    {
        "S.No.": "13",
        "Court": "High Court",
        "Agency State": "MADHYA PRADESH",
        "Agency Code": "HIGH COURT OF M.P PRINCIPAL SEAT AT JABALPUR",
        "Case No.": "WP-12520-2014",
        "Order Date": "08-03-2018",
        "CNR No. /                    Designation": "111",
        "Judge1/ Judge2/ Judge3": "VIJAY KUMAR SHUKLA",
        "Police Station": "",
        "Crime No./ Year": "/ 0",
        "Authority / Organisation / Impugned Order No.": "-//",
        "Judgment Challenged": "No",
        "Judgment Type": "-",
        "Judgment Covered in": "",
        "Vehicle Number": "",
        "Reference court / State / District / No.": "- / - / - / --",
        "Relied Upon court / State / District / No.": "- / - / - / --",
        "Transfer To State / District / No.": "- / - / --",
        "Government Notification State / No. / Date": "- / -- / -"
    },
    {
        "S.No.": "14",
        "Court": "High Court",
        "Agency State": "MADHYA PRADESH",
        "Agency Code": "HIGH COURT OF M.P PRINCIPAL SEAT AT JABALPUR",
        "Case No.": "WP-10919-2014",
        "Order Date": "08-03-2018",
        "CNR No. /                    Designation": "111",
        "Judge1/ Judge2/ Judge3": "VIJAY KUMAR SHUKLA",
        "Police Station": "",
        "Crime No./ Year": "/ 0",
        "Authority / Organisation / Impugned Order No.": "-//",
        "Judgment Challenged": "No",
        "Judgment Type": "-",
        "Judgment Covered in": "",
        "Vehicle Number": "",
        "Reference court / State / District / No.": "- / - / - / --",
        "Relied Upon court / State / District / No.": "- / - / - / --",
        "Transfer To State / District / No.": "- / - / --",
        "Government Notification State / No. / Date": "- / -- / -"
    }
]