{
    "diary_number": "72122022",
    "filed_on": "07-03-2022 11:46 AM",
    "slp_no": "",
    "registered_on": "10-03-2022",
    "verified_on": "12-03-2022",
    "last_listed_on": "",
    "last_hearing_judges": "",
    "status": "PENDING (Motion Hearing   [FRESH (FOR ADMISSION) - CIVIL CASES])  ",
    "tentative_date": "",
    "category": "0812-Letter Petition & Pil Matters : Others",
    "act": "",
    "petitioner": [
        "PARTHVI AHUJA S/D/W/Thru:- V.K. AHUJA",
        "PRAPTI SINGH S/D/W/Thru:- A.K. SINGH"
    ],
    "respondents": [
        "UNION OF INDIA",
        "UNION OF INDIA THR. ITS SECRETARY MINISTRY OF HIGHER EDUCATION",
        "UNION OF INDIA THR. SECRETARY MINISTRY OF EXTERNAL AFFAIRS",
        "NATIONAL MEDICAL COMMISSION",
        "UNIVERSITY GRANTS COMMISSION (UGC)",
        "THE STATE OF ANDHRA PRADESH",
        "THE STATE OF ARUNACHAL PRADESH",
        "THE STATE OF ASSAM",
        "THE STATE OF BIHAR",
        "THE STATE OF CHHATTISGARH",
        "THE STATE OF GOA",
        "THE STATE OF GUJARAT",
        "THE STATE OF HARYANA",
        "THE STATE OF HIMACHAL PRADESH",
        "THE STATE OF JHARKHAND",
        "THE STATE OF KARNATAKA",
        "THE STATE OF KERALA",
        "THE STATE OF MADHYA PRADESH",
        "THE STATE OF MAHARASHTRA",
        "THE STATE OF MANIPUR",
        "THE STATE OF MEGHALAYA",
        "STATE OF MIZORAM",
        "STATE OF NAGALAND",
        "STATE OF ODISHA",
        "STATE OF PUNJAB",
        "STATE OF RAJASTHAN",
        "STATE OF SIKKIM",
        "STATE OF TAMIL NADU",
        "STATE OF TELANGANA",
        "STATE OF TRIPURA",
        "STATE OF UTTARAKHAND",
        "STATE OF UTTAR PRADESH",
        "STATE OF WEST BENGAL",
        "UNION TERRITORY OF ANDAMAN AND NICOBAR ISLANDS",
        "UNION TERRITORY OF CHANDIGARH",
        "UNION TERRITORY OF DADRA AND NAGAR HAVELI",
        "UNION TERRITORY OF DAMAN AND DIU",
        "UNION TERRITORY OF NCT OF DELHI",
        "UNION TERRITORY OF JAMMU AND KASHMIR",
        "UNION TERRITORY OF JAMMU AND KASHMIR",
        "UNION TERRITORY OF LADAKH",
        "UNION TERRITORY OF LAKSHADWEEP",
        "UNION TERRITORY OF PUDUCHERRY"
    ],
    "pet_advocate": [
        "PRAKASH AWASTHI"
    ],
    "resp_advocate": [],
    "u_section": " "
}