{
    "INTERLOCUTARY APPLICATION(s)": {
        "0": {
            "Reg. No./I.A. No.": "36593/2022",
            "Particular": "EXEMPTION FROM FILING AFFIDAVIT",
            "Remark": "",
            "Filed By": "ANOOP PRAKASH AWASTHI",
            "Filing Date": "10-03-2022",
            "Sr. No.": "1",
            "Status.": "P",
            "Entered On": "10-03-2022 14:23:21"
        },
        "1": {
            "Reg. No./I.A. No.": "38377/2022",
            "Particular": "INTERVENTION/IMPLEADMENT",
            "Remark": "",
            "Filed By": "ANOOP PRAKASH AWASTHI",
            "Filing Date": "14-03-2022",
            "Sr. No.": "2",
            "Status.": "P",
            "Entered On": "14-03-2022 11:39:50"
        }
    },
    "OTHER DOCUMENT(s)": {
        "0": {
            "Doc. No.": "38375/2022",
            "Document Type": "VAKALATNAMA AND MEMO OF APPEARANCE",
            "Filed By": "ANOOP PRAKASH AWASTHI",
            "Filing Date": "14-03-2022 11:39 AM",
            "Enter By": "AJAY SHUKLA14-03-2022 11:39 AM"
        }
    }
}