[
    {
        "CL Date": "17-02-2021",
        "Misc./Regular": "Misc.",
        "Stage": "[DIRECTION MATTERS]",
        "Purpose": "Ordinary",
        "Proposed/ List in": "Chamber",
        "Judges": "HON'BLE MR. JUSTICE NAVIN SINHA",
        "IA": "",
        "Remarks": "List After (Weeks) [4]",
        "Listed": "LISTED"
    },
    {
        "CL Date": "03-02-2020",
        "Misc./Regular": "Misc.",
        "Stage": "[DIRECTION MATTERS]",
        "Purpose": "Ordinary",
        "Proposed/ List in": "Chamber",
        "Judges": "HON'BLE MR. JUSTICE S. RAVINDRA BHAT",
        "IA": "",
        "Remarks": "List Before Chamber [As per R/P]",
        "Listed": "LISTED"
    },
    {
        "CL Date": "29-11-2019",
        "Misc./Regular": "Misc.",
        "Stage": "[DIRECTION MATTERS]",
        "Purpose": "Ordinary",
        "Proposed/ List in": "Chamber",
        "Judges": "HON'BLE MR. JUSTICE DINESH MAHESHWARI",
        "IA": "",
        "Remarks": "",
        "Listed": "LISTED"
    },
    {
        "CL Date": "25-09-2019",
        "Misc./Regular": "Misc.",
        "Stage": "[SERVICE/COMPLIANCE]-BEFORE REGISTRAR(J) ",
        "Purpose": "Fixed Date by Court",
        "Proposed/ List in": "Registrar",
        "Judges": "REGISTRAR (J-V)",
        "IA": "",
        "Remarks": "",
        "Listed": "LISTED"
    },
    {
        "CL Date": "25-04-2019",
        "Misc./Regular": "Misc.",
        "Stage": "[SERVICE/COMPLIANCE]-BEFORE REGISTRAR(J) ",
        "Purpose": "Ordinary",
        "Proposed/ List in": "Registrar",
        "Judges": "REGISTRAR (A-J)",
        "IA": "",
        "Remarks": "List On (Date) [25-09-2019]",
        "Listed": "LISTED"
    },
    {
        "CL Date": "16-05-2018",
        "Misc./Regular": "Misc.",
        "Stage": "[DEFAULT / OTHER MATTERS]",
        "Purpose": "Ordinary",
        "Proposed/ List in": "Registrar",
        "Judges": "REGISTRAR (J) - IV",
        "IA": "",
        "Remarks": "List before court/bench",
        "Listed": "LISTED"
    }
]