{
    "0": {
        "": "M",
        "Case No.": "23727/2021(25-10-2021 04:54 PM)SLP(C) No. 017134 -  / 2021  Registered on 25-10-2021",
        "Petitioner vs. Respondant": "STATE OF HARYANA vs.GURMAIL KAUR",
        "List": "-",
        "Status": "P",
        "Stat. Info.": "FOR ADMISSION and I.R. and IA No.139930/2021-PERMISSION TO FILE ADDITIONAL DOCUMENTS/FACTS/ANNEXURES",
        "IA": "139930/2021 (P) PERMISSION TO FILE ADDITIONAL DOCUMENTS/FACTS/ANNEXURES154408/2021 (P) INTERVENTION/IMPLEADMENT154420/2021 (P) INTERVENTION/IMPLEADMENT",
        "Entry Date": ""
    },
    "1": {
        "": "L",
        "Case No.": "12646/2022(30-04-2022 12:26 PM)SLP(C) No. 008283 - 008286 / 2022  Registered on 30-04-2022",
        "Petitioner vs. Respondant": "THE STATE OF HARYANA vs.ARPANA YADAV",
        "List": "Y",
        "Status": "P",
        "Stat. Info.": "FOR \nFOR EXEMPTION FROM FILING C/C OF THE IMPUGNED JUDGMENT ON IA 66852/2022 \nFOR APPLICATION FOR PERMISSION ON IA 68276/2022",
        "IA": "66852/2022 (P) EXEMPTION FROM FILING C/C OF THE IMPUGNED JUDGMENT68276/2022 (P) APPLICATION FOR PERMISSION",
        "Entry Date": "17-05-2022 12:56 PM"
    }
}